sparse_filter_convolution/__init__.py
sparse_filter_convolution/sparse_filter_convolution.py
sparse_filter_convolution/sparse_unfold.py
sparse_filter_convolution/sparse_unfold_cuda_ext.cp39-win_amd64.pyd
sparse_filter_convolution-0.1.0.dist-info/METADATA
sparse_filter_convolution-0.1.0.dist-info/WHEEL
sparse_filter_convolution-0.1.0.dist-info/top_level.txt
sparse_filter_convolution-0.1.0.dist-info/RECORD
