Metadata-Version: 2.1
Name: sparse-filter-convolution
Version: 0.1.0
Summary: A CUDA extension for PyTorch to perform sparse filter convolution
Home-page: https://github.com/tobiaskatsch/sparse_filter_convolution.git
Author: Tobias Katsch
Author-email: tobias.katsch42@gmail.com
Requires-Dist: torch
